itnpy/__init__.py
itnpy/_version.py
itnpy/custom.py
itnpy/itn.py
itnpy/vocab.py
itnpy2-0.0.7.dist-info/LICENSE
itnpy2-0.0.7.dist-info/METADATA
itnpy2-0.0.7.dist-info/WHEEL
itnpy2-0.0.7.dist-info/top_level.txt
itnpy2-0.0.7.dist-info/RECORD
