Metadata-Version: 2.1
Name: itnpy2
Version: 0.0.7
Summary: A simple, deterministic, and extensible approach to inverse text normalization for numbers
Home-page: https://github.com/barseghyanartur/itnpy
Author: Brandhsu
Author-email: brandondhsu@gmail.com
Maintainer: Artur Barseghyan
Maintainer-email: artur.barseghyan@gmail.com
License: MIT
Project-URL: Bug Tracker, https://github.com/barseghyanartur/itnpy/issues
Project-URL: Documentation, https://itnpy2.readthedocs.io/
Project-URL: Source Code, https://github.com/barseghyanartur/itnpy
Project-URL: Changelog, https://itnpy2.readthedocs.io/en/latest/changelog.html
Keywords: inverse text normalization,natural language processing,speech recognition,itn,nlp,asr
Classifier: Development Status :: 3 - Alpha
Classifier: Intended Audience :: Developers
Classifier: License :: OSI Approved :: MIT License
Classifier: Programming Language :: Python :: 3.7
Classifier: Programming Language :: Python :: 3.8
Classifier: Programming Language :: Python :: 3.9
Classifier: Programming Language :: Python :: 3.10
Classifier: Programming Language :: Python :: 3.11
Requires-Python: >=3.7
License-File: LICENSE
Requires-Dist: numpy
Requires-Dist: pandas
